<properties version="1.0">
	<!-- TCS EDIT -->

	<!-- TITLEBAR -->
	<colour name="tcs_bg" 																	value="rgb(32,34,36)" />
	<colour name="tcs_bg_lighter" 													value="rgb(42,44,46)" />	
	<colour name="tcs_accent" 													value="rgb(55,175,247)" />	

	<!-- ACCENT COLOURS -->  
	<colour name="fg accent" 													value="tcs_accent" />
	<colour name="bg accent" 													value="tcs_accent" />
	<colour name="title" 													value="tcs_accent" />

	<!-- TWITTER -->
	<colour name="twitter" value="rgb(23,160,238)"/>
	<colour name="twitter_base_font" value="rgb(101,119,134)"/>

</properties>